{
    "마구로테이블": {
        "rank": "4.9",
        "location": "부산 해운대구 청사포로 157"
    },
    "도희네 조개구이": {
        "rank": "4.21",
        "location": "부산 수영구 광안해변로344번길 17-20 풍경타워 8층 광안리 산해횟집"
    },
    "광안리 산해횟집": {
        "rank": "4.51",
        "location": "부산 수영구 광안해변로344번길 17-20 풍경타워 8층 광안리 산해횟집"
    },
    "자갈치횟집": {
        "rank": "4.46",
        "location": "부산 해운대구 달맞이길62번길 67"
    },
    "선창횟집": {
        "rank": "4.23",
        "location": "부산 부산진구 중앙대로692번길 39"
    },
    "회사원": {
        "rank": "4.41",
        "location": "부산 수영구 광안해변로344번길 17-20 풍경타워 4층 광안리 진양호횟집"
    },
    "광안리 진양호횟집": {
        "rank": "4.62",
        "location": "부산 수영구 광안해변로344번길 17-11 5층"
    },
    "광안리 해린횟집": {
        "rank": "4.7",
        "location": "부산 수영구 민락수변로 103 밀레니엄프라자"
    },
    "광안리길수횟집": {
        "rank": "4.3",
        "location": "부산 연제구 고분로13번길 78 1층"
    },
    "도심속바다": {
        "rank": "4.53",
        "location": "부산 해운대구 해운대로608번길 36 비치24스토아"
    },
    "오빠야횟집 1호해운대점": {
        "rank": "4.36",
        "location": "부산 수영구 민락수변로 1 민락타운"
    },
    "민락회타운": {
        "rank": "4.36",
        "location": "부산 수영구 광안해변로344번길 17-11 나포리B/D 7층 유가횟집"
    },
    "광안리 유가횟집": {
        "rank": "4.79",
        "location": "부산 중구 자갈치해안로 55"
    },
    "부산명물횟집": {
        "rank": "4.14",
        "location": "부산 수영구 광안해변로344번길 17-5 마린리치건물6층 금랑횟집"
    },
    "금랑횟집 광안리본점": {
        "rank": "4.62",
        "location": "부산 중구 자갈치로47번길 4"
    },
    "부산횟집": {
        "rank": "4.16",
        "location": "부산 수영구 광안해변로 263"
    },
    "해운마루": {
        "rank": "4.49",
        "location": "부산 해운대구 해운대해변로221번길 15"
    },
    "대게좋아 일월성": {
        "rank": "3.54",
        "location": "부산 해운대구 해운대해변로209번나길 17 우동 근생"
    },
    "동백섬횟집": {
        "rank": "4.21",
        "location": "부산 수영구 광안해변로 207 W모텔 1층"
    },
    "진미횟집": {
        "rank": "4.34",
        "location": "부산 부산진구 중앙대로691번가길 24-13"
    },
    "막썰어파는횟집 서면점": {
        "rank": "4.34",
        "location": "부산 동래구 명장로 151 1층 OK도매횟집 안락점"
    },
    "OK도매횟집 안락점": {
        "rank": "4.8",
        "location": "부산 중구 중앙대로 2 롯데백화점광복점 10층"
    },
    "모시모시 롯데백화점광복점": {
        "rank": "4.39",
        "location": "부산 부산진구 동천로95번길 10"
    },
    "자갈치1호 서면본점": {
        "rank": "4.31",
        "location": "부산 수영구 남천동로9번길 50"
    },
    "퇴근길자연산횟집": {
        "rank": "4.53",
        "location": "부산 기장군 기장읍 기장해안로 572 남항횟집"
    },
    "남항횟집": {
        "rank": "4.4",
        "location": "부산 수영구 광안해변로278번길 22"
    },
    "삼삼횟집": {
        "rank": "4.18",
        "location": "부산 중구 광복로12번길 3-2 멕코이치킨 앞 골목 안쪽"
    },
    "청조횟집": {
        "rank": "4.51",
        "location": "부산 동래구 명륜로139번길 45 1층 102,103호"
    },
    "동래막썰어횟집": {
        "rank": "4.33",
        "location": "부산 중구 구덕로 40 남포문고 13층"
    },
    "하늘어장": {
        "rank": "4.23",
        "location": "부산 해운대구 달맞이길62번길 28 1층 부산횟집"
    },
    "칠성횟집": {
        "rank": "4.07",
        "location": "부산 중구 자갈치해안로 52 자갈치시장"
    },
    "달봉이횟집": {
        "rank": "4.44",
        "location": "부산 수영구 민락수변로 25"
    },
    "자연활어 수정궁": {
        "rank": "4.36",
        "location": "부산 동래구 동래로 137"
    },
    "영광횟집": {
        "rank": "4.28",
        "location": "부산 수영구 민락수변로 1 민락타운 9층 오륙도횟집"
    },
    "오륙도 횟집": {
        "rank": "4.44",
        "location": "부산 동래구 금강로74번길 30"
    },
    "청정바다": {
        "rank": "4.32",
        "location": "부산 해운대구 마린시티3로 52 한화리조트 2F 블루시걸"
    },
    "피쉬 앤 시사이드 키친": {
        "rank": "4.47",
        "location": "부산 해운대구 해운대해변로209번길 22"
    },
    "해운대다찌": {
        "rank": "4.34"
    },
    "해왕상회": {
        "rank": "4.43",
        "location": "부산 해운대구 우동1로 46"
    },
    "박선장횟집": {
        "rank": "4.07",
        "location": "부산 기장군 일광면 문오성길 509 꺼먹동네횟집"
    },
    "꺼먹동네": {
        "rank": "4.21"
    },
    "칠암등대횟집": {
        "rank": "4.4",
        "location": "부산 해운대구 청사포로 161 바닷가횟집"
    },
    "착한횟집": {
        "rank": "3.97",
        "location": "부산 해운대구 달맞이길62번길 46 이씨할매횟집"
    },
    "이씨할매횟집": {
        "rank": "4.14"
    },
    "까치횟집": {
        "rank": "4.48",
        "location": "부산 동래구 온천천로 157"
    },
    "우럭만공격 동래점": {
        "rank": "4.37",
        "location": "부산 남구 동명로158번길 64"
    },
    "어맛횟집": {
        "rank": "4.23",
        "location": "부산 금정구 남산로 3"
    },
    "홍이네횟집": {
        "rank": "4.29",
        "location": "부산 남구 백운포로 39-18"
    },
    "진주횟집": {
        "rank": "4.42"
    },
    "청해수산횟집": {
        "rank": "4.02"
    }
}